odoo/addons/account_analytic_wip/README.rst
odoo/addons/account_analytic_wip/__init__.py
odoo/addons/account_analytic_wip/__manifest__.py
odoo/addons/account_analytic_wip/data/ir_config_parameter_data.xml
odoo/addons/account_analytic_wip/data/ir_cron_data.xml
odoo/addons/account_analytic_wip/demo/product_demo.xml
odoo/addons/account_analytic_wip/i18n/account_analytic_wip.pot
odoo/addons/account_analytic_wip/i18n/fr.po
odoo/addons/account_analytic_wip/i18n/fr_FR.po
odoo/addons/account_analytic_wip/i18n/sv.po
odoo/addons/account_analytic_wip/models/__init__.py
odoo/addons/account_analytic_wip/models/account_analytic.py
odoo/addons/account_analytic_wip/models/account_analytic_line.py
odoo/addons/account_analytic_wip/models/account_analytic_tracking.py
odoo/addons/account_analytic_wip/models/account_move.py
odoo/addons/account_analytic_wip/models/product_category.py
odoo/addons/account_analytic_wip/readme/CONFIGURATION.rst
odoo/addons/account_analytic_wip/readme/CONTRIBUTORS.rst
odoo/addons/account_analytic_wip/readme/DESCRIPTION.rst
odoo/addons/account_analytic_wip/readme/USAGE.rst
odoo/addons/account_analytic_wip/security/ir.model.access.csv
odoo/addons/account_analytic_wip/static/description/icon.png
odoo/addons/account_analytic_wip/static/description/index.html
odoo/addons/account_analytic_wip/tests/__init__.py
odoo/addons/account_analytic_wip/tests/test_analytic.py
odoo/addons/account_analytic_wip/views/account_analytic_line.xml
odoo/addons/account_analytic_wip/views/account_analytic_tracking.xml
odoo/addons/account_analytic_wip/views/account_move.xml
odoo/addons/account_analytic_wip/views/product_category_view.xml
odoo14_addon_account_analytic_wip-14.0.3.0.3.dist-info/METADATA
odoo14_addon_account_analytic_wip-14.0.3.0.3.dist-info/WHEEL
odoo14_addon_account_analytic_wip-14.0.3.0.3.dist-info/top_level.txt
odoo14_addon_account_analytic_wip-14.0.3.0.3.dist-info/RECORD
