Metadata-Version: 2.1
Name: odoo14-addon-account-analytic-wip
Version: 14.0.3.0.3
Summary: Track and report WIP and Variances based on Analytic Items
Home-page: https://github.com/OCA/account-analytic
Author: Open Source Integrators, Odoo Community Association (OCA)
Author-email: support@odoo-community.org
License: AGPL-3
Platform: UNKNOWN
Classifier: Programming Language :: Python
Classifier: Framework :: Odoo
Classifier: Framework :: Odoo :: 14.0
Classifier: License :: OSI Approved :: GNU Affero General Public License v3
Classifier: Development Status :: 3 - Alpha
Requires-Python: >=3.6
Requires-Dist: odoo14-addon-analytic-activity-based-cost
Requires-Dist: odoo <14.1dev,>=14.0a
